[
  {
    "sheetId": "marketing-sheet",
    "sheetRowKey": "row-instagram",
    "platform": "instagram",
    "accountId": "acct-instagram-demo",
    "syncedAt": "2026-03-25T03:57:13.616Z",
    "rows": []
  },
  {
    "sheetId": "marketing-sheet",
    "sheetRowKey": "row-facebook",
    "platform": "facebook",
    "accountId": "acct-facebook-demo",
    "syncedAt": "2026-03-25T03:57:13.784Z",
    "rows": []
  },
  {
    "sheetId": "marketing-sheet",
    "sheetRowKey": "row-tiktok",
    "platform": "tiktok",
    "accountId": "acct-tiktok-demo",
    "syncedAt": "2026-03-25T03:57:13.908Z",
    "rows": []
  }
]
